<?xml version="1.0" encoding="UTF-8"?>
    <addon id="repository.JimmyS84private" name="JimmyS84 private repository" version="1.0.0" provider-name="JimmyS84">
        <requires>
            <import addon="xbmc.addon" version="12.0.0"/>
        </requires>
        <extension point="xbmc.addon.repository" name="JimmyS84 repository">
            <info compressed="false">https://jirik.php5.cz/storage/repository.JimmySprivate/addons.xml</info>
            <checksum>https://jirik.php5.cz/storage/repository.JimmySprivate/addons.xml.md5</checksum>
            <datadir zip="true">https://jirik.php5.cz/storage/repository.JimmySprivate/</datadir>
            <hashes>false</hashes>
        </extension>
        <extension point="xbmc.addon.metadata">
            <summary>JimmyS84 Private Addons</summary>
            <description>Improved things for Kodi.</description>
            <platform>all</platform>
    </extension>
</addon>